quxr/__init__.py
quxr-0.0.1.dist-info/LICENSE
quxr-0.0.1.dist-info/METADATA
quxr-0.0.1.dist-info/WHEEL
quxr-0.0.1.dist-info/RECORD
