Metadata-Version: 2.1
Name: quxr
Version: 0.0.1
Summary: This package contains methods used in Quantitive UX Research
License: MIT
Author: Mason Sun
Author-email: masonzsun@gmail.com
Requires-Python: >=3.9,<4.0
Classifier: License :: OSI Approved :: MIT License
Classifier: Programming Language :: Python :: 3
Classifier: Programming Language :: Python :: 3.9
Classifier: Programming Language :: Python :: 3.10
Classifier: Programming Language :: Python :: 3.11
Requires-Dist: pandas (>=2.0.3,<3.0.0)
